{"gmina": "gmina miejsko-wiejska Krzy\u017c Wielkopolski", "ludnosc": 8780, "budzet": {"dochody": "40,14 mln z\u0142", "wydatki": "37,90 mln z\u0142"}, "gospodarka_odpadami_komunalnymi": {"dochody": "0,00 tys z\u0142", "wydatki": "0,00 tys z\u0142"}, "dochod_ue": "148,32 tys z\u0142", "wydatki_biezace_ue": "203,87 tys z\u0142", "wydatki_inwestycje_ue": "327,46 tys z\u0142", "janosik": {"dochody": "4,29 mln z\u0142", "wydatki": "0"}, "projekty_ue": [], "children": [{"name": "O\u015bwiata i wychowanie", "v": "12,78 mln z\u0142", "procent": 33.73, "v_pc": "1455,93 z\u0142", "pl_v_pc": "1975,10 z\u0142", "v_pc_diff": "26.2% ", "v_pc_diff_word": "mniej", "children": [{"name": "Szko\u0142y podstawowe", "v": "6,10 mln z\u0142", "procent": 47.74}, {"name": "Przedszkola", "v": "2,93 mln z\u0142", "procent": 22.88}, {"name": "Gimnazja", "v": "1,22 mln z\u0142", "procent": 9.56}, {"name": "Licea og\u00f3lnokszta\u0142c\u0105ce", "v": "901,80 tys z\u0142", "procent": 7.05}, {"name": "Nauka specjalna w SP", "v": "864,64 tys z\u0142", "procent": 6.76}, {"name": "Dowo\u017cenie uczni\u00f3w do szk\u00f3\u0142", "v": "258,29 tys z\u0142", "procent": 2.02}, {"name": "Nauka specjalna w szko\u0142ach \u015brednich", "v": "231,47 tys z\u0142", "procent": 1.81}, {"name": "Pozosta\u0142a dzia\u0142alno\u015b\u0107", "v": "79,97 tys z\u0142", "procent": 0.62}, {"name": "Podr\u0119czniki dla szk\u00f3\u0142 podstawowych", "v": "67,30 tys z\u0142", "procent": 0.52}, {"name": "Oddzia\u0142y przedszkolne w SP", "v": "62,37 tys z\u0142", "procent": 0.48}, {"name": "Nauka specjalna w przedszkolach", "v": "33,52 tys z\u0142", "procent": 0.26}, {"name": "Dokszta\u0142canie nauczycieli", "v": "32,40 tys z\u0142", "procent": 0.25}]}, {"name": "Rodzina", "v": "11,07 mln z\u0142", "procent": 29.21, "v_pc": "1260,97 z\u0142", "pl_v_pc": "1300,91 z\u0142", "v_pc_diff": "3.0% ", "v_pc_diff_word": "mniej", "children": [{"name": "\u015awiadczenie wychowawcze", "v": "6,92 mln z\u0142", "procent": 62.48}, {"name": "\u015awiadczenia rodzinne, alimenty i spo\u0142eczne sk\u0142adki", "v": "3,07 mln z\u0142", "procent": 27.72}, {"name": "NIEZNANY2", "v": "613,51 tys z\u0142", "procent": 5.54}, {"name": "Wspieranie rodziny", "v": "382,51 tys z\u0142", "procent": 3.45}, {"name": "Rodziny zast\u0119pcze", "v": "44,02 tys z\u0142", "procent": 0.39}, {"name": "Zdrowotne za osoby na rodzinnym/opieku\u0144czym", "v": "41,27 tys z\u0142", "procent": 0.37}, {"name": "Karta Du\u017cej Rodziny", "v": "2,20 tys z\u0142", "procent": 0.01}]}, {"name": "Administracja publiczna", "v": "3,80 mln z\u0142", "procent": 10.01, "v_pc": "432,34 z\u0142", "pl_v_pc": "584,24 z\u0142", "v_pc_diff": "25.9% ", "v_pc_diff_word": "mniej", "children": [{"name": "Urz\u0119dy gmin (miast i miast na prawach powiatu)", "v": "3,19 mln z\u0142", "procent": 84.13}, {"name": "Pozosta\u0142a dzia\u0142alno\u015b\u0107", "v": "271,29 tys z\u0142", "procent": 7.14}, {"name": "Rady gmin (miast i miast na prawach powiatu)", "v": "199,42 tys z\u0142", "procent": 5.25}, {"name": "Urz\u0119dy wojew\u00f3dzkie", "v": "88,72 tys z\u0142", "procent": 2.33}, {"name": "Promocja jednostek samorz\u0105du terytorialnego", "v": "42,40 tys z\u0142", "procent": 1.11}, {"name": "Kwalifikacja wojskowa", "v": "0,38 tys z\u0142", "procent": 0.01}]}, {"name": "Gospodarka komunalna i ochrona \u015brodowiska", "v": "2,39 mln z\u0142", "procent": 6.31, "v_pc": "272,70 z\u0142", "pl_v_pc": "537,97 z\u0142", "v_pc_diff": "49.3% ", "v_pc_diff_word": "mniej", "children": [{"name": "Zak\u0142ady gospodarki komunalnej", "v": "978,07 tys z\u0142", "procent": 40.84}, {"name": "Gospodarka \u015bciekowa i ochrona w\u00f3d", "v": "510,05 tys z\u0142", "procent": 21.3}, {"name": "O\u015bwietlenie ulic, plac\u00f3w i dr\u00f3g", "v": "350,37 tys z\u0142", "procent": 14.63}, {"name": "Pozosta\u0142a dzia\u0142alno\u015b\u0107", "v": "254,42 tys z\u0142", "procent": 10.62}, {"name": "Ochrona gleby i w\u00f3d podziemnych", "v": "79,07 tys z\u0142", "procent": 3.3}, {"name": "Schroniska dla zwierz\u0105t", "v": "78,13 tys z\u0142", "procent": 3.26}, {"name": "Oczyszczanie miast i wsi", "v": "53,73 tys z\u0142", "procent": 2.24}, {"name": "Utrzymanie zieleni w miastach i gminach", "v": "45,26 tys z\u0142", "procent": 1.89}, {"name": "Pozosta\u0142e dzia\u0142ania zwi\u0105zane z gospodark\u0105 odpadami", "v": "45,24 tys z\u0142", "procent": 1.88}]}, {"name": "Pomoc spo\u0142eczna", "v": "2,32 mln z\u0142", "procent": 6.12, "v_pc": "264,17 z\u0142", "pl_v_pc": "385,97 z\u0142", "v_pc_diff": "31.5% ", "v_pc_diff_word": "mniej", "children": [{"name": "O\u015brodki pomocy spo\u0142ecznej", "v": "875,21 tys z\u0142", "procent": 37.73}, {"name": "Domy pomocy spo\u0142ecznej", "v": "481,40 tys z\u0142", "procent": 20.75}, {"name": "Zasi\u0142ki okresowe, celowe i pomoc w naturze oraz sk\u0142adki", "v": "349,34 tys z\u0142", "procent": 15.06}, {"name": "Zasi\u0142ki sta\u0142e", "v": "271,42 tys z\u0142", "procent": 11.7}, {"name": "Pomoc w zakresie do\u017cywiania", "v": "145,81 tys z\u0142", "procent": 6.28}, {"name": "Dodatki mieszkaniowe", "v": "132,00 tys z\u0142", "procent": 5.69}, {"name": "Pozosta\u0142a dzia\u0142alno\u015b\u0107", "v": "27,71 tys z\u0142", "procent": 1.19}, {"name": "Sk\u0142adki zdrowotne za osoby korzystaj\u0105ce z pomocy spo\u0142ecznej", "v": "23,59 tys z\u0142", "procent": 1.01}, {"name": "Us\u0142ugi opieku\u0144cze i specjalistyczne us\u0142ugi opieku\u0144cze", "v": "12,15 tys z\u0142", "procent": 0.52}, {"name": "Przeciwdzia\u0142anie przemocy w rodzinie", "v": "0,78 tys z\u0142", "procent": 0.03}]}, {"name": "Rolnictwo i \u0142owiectwo", "v": "1,19 mln z\u0142", "procent": 3.13, "v_pc": "135,18 z\u0142", "pl_v_pc": "105,93 z\u0142", "v_pc_diff": "27.6% ", "v_pc_diff_word": "wi\u0119cej", "children": [{"name": "Wy\u0142\u0105czenie z produkcji grunt\u00f3w rolnych", "v": "892,58 tys z\u0142", "procent": 75.2}, {"name": "Pozosta\u0142a dzia\u0142alno\u015b\u0107", "v": "292,33 tys z\u0142", "procent": 24.62}, {"name": "Izby rolnicze", "v": "1,99 tys z\u0142", "procent": 0.16}]}, {"name": "Bezpiecze\u0144stwo publiczne i ochrona ppo\u017c", "v": "795,47 tys z\u0142", "procent": 2.09, "v_pc": "90,60 z\u0142", "pl_v_pc": "129,41 z\u0142", "v_pc_diff": "29.9% ", "v_pc_diff_word": "mniej", "children": [{"name": "Ochotnicze stra\u017ce po\u017carne", "v": "757,42 tys z\u0142", "procent": 95.21}, {"name": "Zarz\u0105dzanie kryzysowe", "v": "15,59 tys z\u0142", "procent": 1.96}, {"name": "Powiatowa Pa\u0144stwowa Stra\u017c Po\u017carna", "v": "15,00 tys z\u0142", "procent": 1.88}, {"name": "Komendy powiatowe Policji", "v": "6,50 tys z\u0142", "procent": 0.81}, {"name": "Pozosta\u0142a dzia\u0142alno\u015b\u0107", "v": "0,96 tys z\u0142", "procent": 0.12}]}, {"name": "Kultura i ochrona dziedzictwa narodowego", "v": "753,71 tys z\u0142", "procent": 1.98, "v_pc": "85,84 z\u0142", "pl_v_pc": "251,07 z\u0142", "v_pc_diff": "65.8% ", "v_pc_diff_word": "mniej", "children": [{"name": "Domy i o\u015brodki kultury, \u015bwietlice i kluby", "v": "576,85 tys z\u0142", "procent": 76.53}, {"name": "Biblioteki", "v": "142,35 tys z\u0142", "procent": 18.88}, {"name": "Ochrona zabytk\u00f3w i opieka nad zabytkami", "v": "16,61 tys z\u0142", "procent": 2.2}, {"name": "Pozosta\u0142e zadania w zakresie kultury", "v": "14,00 tys z\u0142", "procent": 1.85}, {"name": "Pozosta\u0142a dzia\u0142alno\u015b\u0107", "v": "3,90 tys z\u0142", "procent": 0.51}]}, {"name": "Edukacyjna opieka wychowawcza", "v": "662,12 tys z\u0142", "procent": 1.74, "v_pc": "75,41 z\u0142", "pl_v_pc": "158,34 z\u0142", "v_pc_diff": "52.3% ", "v_pc_diff_word": "mniej", "children": [{"name": "\u015awietlice szkolne", "v": "531,72 tys z\u0142", "procent": 80.3}, {"name": "Przeciwdzia\u0142anie i ograniczanie skutk\u00f3w patologii spo\u0142ecznej", "v": "73,05 tys z\u0142", "procent": 11.03}, {"name": "Pomoc materialna dla uczni\u00f3w o charakterze socjalnym", "v": "52,26 tys z\u0142", "procent": 7.89}, {"name": "Wczesne wspomaganie rozwoju dziecka", "v": "5,09 tys z\u0142", "procent": 0.76}]}, {"name": "Gospodarka mieszkaniowa", "v": "656,78 tys z\u0142", "procent": 1.73, "v_pc": "74,80 z\u0142", "pl_v_pc": "208,01 z\u0142", "v_pc_diff": "64.0% ", "v_pc_diff_word": "mniej", "children": [{"name": "Gospodarka gruntami i nieruchomo\u015bciami", "v": "656,78 tys z\u0142", "procent": 100.0}]}, {"name": "Transport i \u0142\u0105czno\u015b\u0107", "v": "528,67 tys z\u0142", "procent": 1.39, "v_pc": "60,21 z\u0142", "pl_v_pc": "1117,45 z\u0142", "v_pc_diff": "94.6% ", "v_pc_diff_word": "mniej", "children": [{"name": "Drogi publiczne gminne", "v": "508,02 tys z\u0142", "procent": 96.09}, {"name": "Drogi publiczne wojew\u00f3dzkie", "v": "11,31 tys z\u0142", "procent": 2.13}, {"name": "Drogi publiczne powiatowe", "v": "7,19 tys z\u0142", "procent": 1.35}, {"name": "Pozosta\u0142a dzia\u0142alno\u015b\u0107", "v": "2,15 tys z\u0142", "procent": 0.4}]}, {"name": "ZOO, ogrody botaniczne i obszary chronione", "v": "349,84 tys z\u0142", "procent": 0.92, "v_pc": "39,84 z\u0142", "pl_v_pc": "7,97 z\u0142", "v_pc_diff": "399.8% ", "v_pc_diff_word": "wi\u0119cej", "children": [{"name": "Pozosta\u0142a dzia\u0142alno\u015b\u0107", "v": "349,84 tys z\u0142", "procent": 100.0}]}, {"name": "Kultura fizyczna", "v": "215,76 tys z\u0142", "procent": 0.56, "v_pc": "24,57 z\u0142", "pl_v_pc": "155,99 z\u0142", "v_pc_diff": "84.2% ", "v_pc_diff_word": "mniej", "children": [{"name": "Zadania w zakresie kultury fizycznej", "v": "164,70 tys z\u0142", "procent": 76.33}, {"name": "Obiekty sportowe", "v": "51,06 tys z\u0142", "procent": 23.66}]}, {"name": "Ochrona zdrowia", "v": "116,21 tys z\u0142", "procent": 0.3, "v_pc": "13,24 z\u0142", "pl_v_pc": "117,30 z\u0142", "v_pc_diff": "88.7% ", "v_pc_diff_word": "mniej", "children": [{"name": "Przeciwdzia\u0142anie alkoholizmowi", "v": "107,91 tys z\u0142", "procent": 92.85}, {"name": "Zwalczanie narkomanii", "v": "8,30 tys z\u0142", "procent": 7.14}]}, {"name": "Obs\u0142uga d\u0142ugu publicznego", "v": "114,23 tys z\u0142", "procent": 0.3, "v_pc": "13,01 z\u0142", "pl_v_pc": "54,13 z\u0142", "v_pc_diff": "75.9% ", "v_pc_diff_word": "mniej", "children": [{"name": "Obs\u0142uga kredyt\u00f3w i po\u017cyczek samorz\u0105du", "v": "114,23 tys z\u0142", "procent": 100.0}]}, {"name": "Dzia\u0142alno\u015b\u0107 us\u0142ugowa", "v": "79,33 tys z\u0142", "procent": 0.2, "v_pc": "9,03 z\u0142", "pl_v_pc": "47,80 z\u0142", "v_pc_diff": "81.1% ", "v_pc_diff_word": "mniej", "children": [{"name": "Zadania z zakresu geodezji i kartografii", "v": "52,43 tys z\u0142", "procent": 66.09}, {"name": "Plany zagospodarowania przestrzennego", "v": "23,60 tys z\u0142", "procent": 29.75}, {"name": "Pozosta\u0142a dzia\u0142alno\u015b\u0107", "v": "3,29 tys z\u0142", "procent": 4.15}]}, {"name": "Urz\u0119dy pa\u0144stwowe", "v": "74,11 tys z\u0142", "procent": 0.19, "v_pc": "8,44 z\u0142", "pl_v_pc": "7,49 z\u0142", "v_pc_diff": "12.6% ", "v_pc_diff_word": "wi\u0119cej", "children": [{"name": "Wybory do Sejmu i Senatu", "v": "28,61 tys z\u0142", "procent": 38.6}, {"name": "Wybory do Parlamentu Europejskiego", "v": "27,88 tys z\u0142", "procent": 37.62}, {"name": "Wybory i referenda samorz\u0105dowe", "v": "15,84 tys z\u0142", "procent": 21.37}, {"name": "Urz\u0119dy naczelnych organ\u00f3w w\u0142adzy pa\u0144stwowej, kontroli i ochrony prawa", "v": "1,78 tys z\u0142", "procent": 2.4}]}, {"name": "R\u00f3\u017cne rozliczenia", "v": "0,00 tys z\u0142", "procent": 0.0, "v_pc": "0,00 z\u0142", "pl_v_pc": "73,11 z\u0142", "v_pc_diff": "100.0% ", "v_pc_diff_word": "mniej", "children": []}]}